{
   "Name": "Graphite_Safari2009",
   "Header": {},
   "component": "negative_electrode_active_material",
   "material": true,
   "Parameters": {
      "maximum_concentration": 30555.0,
      "volumetric_surface_area": 723600.0,
      "density": 2240.0,
      "number_of_electrons_transferred": 1,
      "activation_energy_of_reaction": 5000.0,
      "reaction_rate_constant": 5.031e-11,
      "maximum_lithium_stoichiometry": 0.88551,
      "minimum_lithium_stoichiometry": 0.1429,
      "open_circuit_potential": {
         "functionname": "compute_ocp_graphite",
         "argument_list": [
            "cElectrode",
            "T",
            "cmax"
          ]
      }
   }
}